{
  "id": "se-runbook",
  "name": "se-runbook",
  "title": "Implement se-runbook",
  "description": "Add an operational runbook workflow with triggers, preconditions, authority, procedure, decision points, verification, failure handling, escalation, rollback, recovery, and maintenance ownership.",
  "status": "in_progress",
  "dev_type": null,
  "scope": null,
  "package": null,
  "priority": "P2",
  "creator": "sdelmas",
  "assignee": "sdelmas",
  "createdAt": "2026-07-17",
  "completedAt": null,
  "branch": "codex/se-runbook",
  "base_branch": "codex/expand-skill-roadmap",
  "worktree_path": null,
  "commit": null,
  "pr_url": null,
  "subtasks": [],
  "children": [],
  "parent": "07-17-se-skill-roadmap",
  "relatedFiles": [],
  "notes": "",
  "meta": {}
}